PrivateSign/api.py
PrivateSign/signer.cpython-311-darwin.so
PrivateSign-1.1.7.dist-info/RECORD
PrivateSign-1.1.7.dist-info/WHEEL
PrivateSign-1.1.7.dist-info/top_level.txt
PrivateSign-1.1.7.dist-info/METADATA
